iext-1.1.0.dist-info/METADATA
iext-1.1.0.dist-info/WHEEL
iext-1.1.0.dist-info/licenses/LICENSE
iext/__init__.py
iext/importextension.py
iext-1.1.0.dist-info/RECORD
