Metadata-Version: 2.1
Name: iext
Version: 1.1.0
Summary: Python import extension metaclass.
Author-Email: ilikecubesnstuff <25328250+ilikecubesnstuff@users.noreply.github.com>
License: MIT
Classifier: Intended Audience :: Developers
Classifier: Natural Language :: English
Classifier: License :: OSI Approved :: MIT License
Classifier: Programming Language :: Python :: 3 :: Only
Classifier: Programming Language :: Python :: 3.8
Classifier: Programming Language :: Python :: 3.9
Classifier: Programming Language :: Python :: 3.10
Classifier: Programming Language :: Python :: 3.11
Classifier: Programming Language :: Python :: 3.12
Classifier: Topic :: Utilities
Requires-Python: >=3.8
